segments/__init__.py
segments/__main__.py
segments/errors.py
segments/profile.py
segments/tokenizer.py
segments/tree.py
segments/util.py
segments-2.2.1.dist-info/LICENSE
segments-2.2.1.dist-info/METADATA
segments-2.2.1.dist-info/WHEEL
segments-2.2.1.dist-info/entry_points.txt
segments-2.2.1.dist-info/top_level.txt
segments-2.2.1.dist-info/RECORD
