Metadata-Version: 2.1
Name: segments
Version: 2.2.1
Summary: UNKNOWN
Home-page: https://github.com/cldf/segments
Author: Steven Moran and Robert Forkel
Author-email: steven.moran@uzh.ch
License: Apache 2.0
Keywords: tokenizer
Platform: UNKNOWN
Classifier: Development Status :: 4 - Beta
Classifier: Intended Audience :: Developers
Classifier: License :: OSI Approved :: Apache Software License
Classifier: Natural Language :: English
Classifier: Programming Language :: Python :: 3
Classifier: Programming Language :: Python :: 3.7
Classifier: Programming Language :: Python :: 3.8
Classifier: Programming Language :: Python :: 3.9
Classifier: Programming Language :: Python :: 3.10
Classifier: Programming Language :: Python :: Implementation :: CPython
Classifier: Programming Language :: Python :: Implementation :: PyPy
Provides-Extra: dev
Provides-Extra: test
